ocrd_fileformat/__init__.py
ocrd_fileformat/ocrd-tool.json
ocrd_fileformat/processor.py
ocrd_fileformat-0.12.0.dist-info/licenses/LICENSE
ocrd_fileformat-0.12.0.dist-info/METADATA
ocrd_fileformat-0.12.0.dist-info/WHEEL
ocrd_fileformat-0.12.0.dist-info/entry_points.txt
ocrd_fileformat-0.12.0.dist-info/top_level.txt
ocrd_fileformat-0.12.0.dist-info/RECORD
