Metadata-Version: 2.4
Name: ocrd_fileformat
Version: 0.12.0
Summary: OCR-D wrapper for ocr-fileformat
Author-email: Konstantin Baierer <unixprog@gmail.com>, Robert Sachunsky <sachunsky@informatik.uni-leipzig.de>
License: Apache License 2.0
Project-URL: Homepage, https://github.com/OCR-D/ocrd_fileformat
Project-URL: Repository, https://github.com/OCR-D/ocrd_fileformat.git
Keywords: ocr,ocr-d
Classifier: Development Status :: 5 - Production/Stable
Classifier: Environment :: Console
Classifier: Intended Audience :: Science/Research
Classifier: Intended Audience :: Other Audience
Classifier: License :: OSI Approved :: Apache Software License
Classifier: Programming Language :: Python :: 3
Classifier: Programming Language :: Python :: 3 :: Only
Classifier: Topic :: Text Processing
Requires-Python: >=3.8
License-File: LICENSE
Requires-Dist: ocrd>=3.3.0
Provides-Extra: test
Requires-Dist: pytest; extra == "test"
Dynamic: license-file
